README.md
setup.cfg
setup.py
allhub/__init__.py
allhub/all_hub.py
allhub/clone.py
allhub/iterator.py
allhub/oauth.py
allhub/response.py
allhub/transform.py
allhub/util.py
allhub.egg-info/PKG-INFO
allhub.egg-info/SOURCES.txt
allhub.egg-info/dependency_links.txt
allhub.egg-info/requires.txt
allhub.egg-info/top_level.txt
allhub/activity/__init__.py
allhub/activity/events.py
allhub/activity/feeds.py
allhub/activity/notifications.py
allhub/activity/starring.py
allhub/activity/watching.py
allhub/apps/__init__.py
allhub/apps/app.py
allhub/apps/events.py
allhub/apps/installations.py
allhub/apps/permission.py
allhub/checks/__init__.py
allhub/checks/check_runs.py
allhub/checks/check_suites.py
allhub/gists/__init__.py
allhub/gists/gist.py
allhub/gists/gist_comments.py
allhub/git_data/__init__.py
allhub/git_data/blobs.py
allhub/git_data/commits.py
allhub/git_data/references.py
allhub/git_data/tags.py
allhub/git_data/trees.py
allhub/interactions/__init__.py
allhub/interactions/org.py
allhub/interactions/repo.py
allhub/interactions/util.py
allhub/issues/__init__.py
allhub/issues/assignees.py
allhub/issues/comments.py
allhub/issues/events.py
allhub/issues/issues.py
allhub/issues/labels.py
allhub/issues/milestones.py
allhub/issues/timeline.py
allhub/migrations/__init__.py
allhub/migrations/organization.py
allhub/migrations/source_imports.py
allhub/migrations/user.py
allhub/misc/__init__.py
allhub/misc/coc.py
allhub/misc/emoji.py
allhub/misc/gitignore.py
allhub/misc/license.py
allhub/misc/markdown.py
allhub/misc/meta.py
allhub/misc/rate_limit.py
allhub/orgs/__init__.py
allhub/orgs/blocking_users.py
allhub/orgs/members.py
allhub/orgs/org.py
allhub/orgs/outside_collab.py
allhub/orgs/webhooks.py
allhub/projects/__init__.py
allhub/projects/cards.py
allhub/projects/collaborators.py
allhub/projects/columns.py
allhub/projects/project.py
allhub/pull_requests/__init__.py
allhub/pull_requests/pull_request.py
allhub/pull_requests/review_comments.py
allhub/pull_requests/review_requests.py
allhub/pull_requests/reviews.py
allhub/reactions/__init__.py
allhub/reactions/reaction.py
allhub/repos/__init__.py
allhub/repos/branches.py
