Metadata-Version: 1.2
Name: allhub
Version: 0.0.4a2
Summary: Interact with Github REST API v3
Home-page: UNKNOWN
Author: Srinivas Reddy Thatiparthy
Author-email: srinivas.thatiparthy@gmail.com
License: PSF
Project-URL: Source, https://github.com/srinivasreddy/allhub
Keywords: scripts utilities github REST API V3
Platform: UNKNOWN
Classifier: Development Status :: 3 - Alpha
Classifier: Programming Language :: Python :: 3.6
Classifier: Programming Language :: Python :: 3.7
Classifier: Programming Language :: Python :: 3 :: Only
Classifier: Operating System :: OS Independent
Classifier: Intended Audience :: Developers
Requires-Python: >=3.6.0
